maxarcat/__init__.py
maxarcat/catalog.py
maxarcat/exceptions.py
maxarcat/version.txt
maxarcat_client/__init__.py
maxarcat_client/api_client.py
maxarcat_client/configuration.py
maxarcat_client/rest.py
maxarcat_client/api/__init__.py
maxarcat_client/api/maxar_extensionaccess_api.py
maxarcat_client/api/maxar_extensionimagegrid_api.py
maxarcat_client/api/maxar_extensionsubcatalog_api.py
maxarcat_client/api/stac_api.py
maxarcat_client/api/staccollection_api.py
maxarcat_client/api/stacitem_api.py
maxarcat_client/models/__init__.py
maxarcat_client/models/any_ofsearch_body.py
maxarcat_client/models/any_ofstac_extensions_items.py
maxarcat_client/models/bbox.py
maxarcat_client/models/bbox_filter.py
maxarcat_client/models/collection.py
maxarcat_client/models/collection_data_access_profile.py
maxarcat_client/models/collection_id.py
maxarcat_client/models/collection_links.py
maxarcat_client/models/collections.py
maxarcat_client/models/collections_array.py
maxarcat_client/models/collections_filter.py
maxarcat_client/models/data_access_policy.py
maxarcat_client/models/data_access_profile.py
maxarcat_client/models/datetime_filter.py
maxarcat_client/models/exception.py
maxarcat_client/models/filter.py
maxarcat_client/models/filter_filter.py
maxarcat_client/models/geo_json_geometry.py
maxarcat_client/models/geo_json_linestring.py
maxarcat_client/models/geo_json_multilinestring.py
maxarcat_client/models/geo_json_multipoint.py
maxarcat_client/models/geo_json_multipolygon.py
maxarcat_client/models/geo_json_point.py
maxarcat_client/models/geo_json_polygon.py
maxarcat_client/models/geometry.py
maxarcat_client/models/healthcheck.py
maxarcat_client/models/id_list.py
maxarcat_client/models/ids.py
maxarcat_client/models/ids_filter.py
maxarcat_client/models/intersects_filter.py
maxarcat_client/models/item.py
maxarcat_client/models/item_assets.py
maxarcat_client/models/item_collection.py
maxarcat_client/models/item_collection_links.py
maxarcat_client/models/item_collection_post.py
maxarcat-0.9.6.dist-info/LICENSE
maxarcat-0.9.6.dist-info/METADATA
maxarcat-0.9.6.dist-info/WHEEL
maxarcat-0.9.6.dist-info/top_level.txt
maxarcat-0.9.6.dist-info/RECORD
