Metadata-Version: 2.1
Name: maxarcat
Version: 0.9.6
Summary: Maxar Catalog Python client
Home-page: https://github.com/Maxar-Corp/maxarcat
Author: Maxar
Classifier: Programming Language :: Python :: 3
Classifier: Operating System :: OS Independent
Classifier: License :: OSI Approved :: MIT License
Classifier: Topic :: Scientific/Engineering :: GIS
Requires-Python: >=3.8
License-File: LICENSE
Requires-Dist: requests
Requires-Dist: certifi
Requires-Dist: python-dateutil
Requires-Dist: six
Requires-Dist: urllib3
